severus/__init__.py
severus/commands/add.py
severus/commands/delete.py
severus/commands/edit.py
severus/commands/env.py
severus/commands/help.py
severus/commands/init.py
severus/commands/list.py
severus/commands/receive.py
severus/commands/search.py
severus/commands/share.py
severus/commands/show.py
severus/utils/auth.py
severus/utils/config.py
severus/utils/encryption.py
severus/utils/helpers.py
severus/utils/info.py
severus/utils/sharing.py
severus/utils/totp.py
severus/utils/vault.py
severus_vault-1.0.0.dist-info/entry_points.txt
severus_vault-1.0.0.dist-info/LICENSE
severus_vault-1.0.0.dist-info/METADATA
severus_vault-1.0.0.dist-info/WHEEL
severus_vault-1.0.0.dist-info/RECORD
