Metadata-Version: 2.3
Name: severus-vault
Version: 1.0.0
Summary: Severus is a local-first CLI tool for developers to securely manage API keys, passwords, environment variables, and sensitive notes without cloud dependencies or master password vulnerabilities.
License: MIT
Author: Ekomobong Archibong
Author-email: 59149177+archie-bryann@users.noreply.github.com
Requires-Python: >=3.13,<4.0
Classifier: License :: OSI Approved :: MIT License
Classifier: Programming Language :: Python :: 3
Classifier: Programming Language :: Python :: 3.13
Requires-Dist: click (>=8.2.1,<9.0.0)
Requires-Dist: cryptography (>=45.0.7,<46.0.0)
Requires-Dist: pyotp (>=2.9.0,<3.0.0)
Requires-Dist: qrcode (>=8.2,<9.0)
Requires-Dist: requests (>=2.32.5,<3.0.0)
